<?xml version="1.0" encoding="UTF-8"?>
<con:operation id="8eee2569-7423-459d-b42b-45e03d1eb081" isOneWay="false" action="" name="downloadAttachment" bindingOperationName="downloadAttachment" type="Request-Response" outputName="downloadAttachmentResponse" inputName="downloadAttachmentRequest" receivesAttachments="false" sendsAttachments="false" xmlns:xsi="http://www.w3.org/2001/XMLSchema-instance" xmlns:con="http://eviware.com/soapui/config"><con:settings id="970dfaec-ab44-4633-814a-3b366f6153ed"><con:setting id="8eee2569-7423-459d-b42b-45e03d1eb081fileName">downloadAttachment</con:setting></con:settings><con:environmentSpec><con:entry environmentId="77263e2f-5622-4bfa-b189-46a6879138dd"><con:authProfile>Inherit From Parent</con:authProfile></con:entry><con:entry environmentId="4635534f-9f44-4239-8f0d-4d0eb5797727"><con:authProfile>Inherit From Parent</con:authProfile></con:entry><con:entry environmentId="dab9f225-084f-482f-b431-f34f78079bd6"><con:authProfile>Inherit From Parent</con:authProfile></con:entry></con:environmentSpec></con:operation>