<?xml version="1.0" encoding="UTF-8"?>
<con:operation id="a5362424-5358-479b-9788-cb04af3849b9" isOneWay="false" action="" name="getRecipientMedications" bindingOperationName="getRecipientMedications" type="Request-Response" outputName="getRecipientMedicationsResponse" inputName="getRecipientMedicationsRequest" receivesAttachments="false" sendsAttachments="false" xmlns:xsi="http://www.w3.org/2001/XMLSchema-instance" xmlns:con="http://eviware.com/soapui/config"><con:settings id="a56693b6-9fb1-49d6-a592-ee9803cdf6b0"><con:setting id="a5362424-5358-479b-9788-cb04af3849b9fileName">getRecipientMedications</con:setting></con:settings><con:environmentSpec><con:entry environmentId="77263e2f-5622-4bfa-b189-46a6879138dd"><con:authProfile>Inherit From Parent</con:authProfile></con:entry><con:entry environmentId="4635534f-9f44-4239-8f0d-4d0eb5797727"><con:authProfile>Inherit From Parent</con:authProfile></con:entry><con:entry environmentId="dab9f225-084f-482f-b431-f34f78079bd6"><con:authProfile>Inherit From Parent</con:authProfile></con:entry></con:environmentSpec></con:operation>